scpapi/__init__.py
scpapi/client.py
scpapi/resource/__init__.py
scpapi/resource/file_storage.py
scpapi/resource/image.py
scpapi/resource/server_group.py
scpapi/resource/subnet.py
scpapi/resource/virtual_server.py
scpapi-0.0.7.dist-info/METADATA
scpapi-0.0.7.dist-info/WHEEL
scpapi-0.0.7.dist-info/top_level.txt
scpapi-0.0.7.dist-info/RECORD
