Metadata-Version: 2.2
Name: scpapi
Version: 0.0.7
Summary: The SCP API for Python
Home-page: https://github.com/set-e/scpapi
Author: jrpark
Author-email: jungryul0515.park@samsung.com
Classifier: Programming Language :: Python :: 3
Classifier: License :: OSI Approved :: MIT License
Classifier: Operating System :: OS Independent
Requires-Python: >=3.9
Requires-Dist: requests>=2.32.3
Dynamic: author
Dynamic: author-email
Dynamic: classifier
Dynamic: description
Dynamic: description-content-type
Dynamic: home-page
Dynamic: requires-dist
Dynamic: requires-python
Dynamic: summary
